setup.cfg
setup.py
bin/lazycred
lazycred/__init__.py
lazycred/lazycred.py
lazycred.egg-info/PKG-INFO
lazycred.egg-info/SOURCES.txt
lazycred.egg-info/dependency_links.txt
lazycred.egg-info/requires.txt
lazycred.egg-info/top_level.txt