Metadata-Version: 1.1
Name: lazycred
Version: 0.2.3
Summary: Minimalistic Credentials Manager based on AWS.
Home-page: https://github.com/2deviant/LazyCred
Author: Val Tenyotkin
Author-email: val@tenyotk.in
License: MIT
Download-URL: https://github.com/2deviant/LazyCred/tarball/0.2.3
Keywords: aws,kms,encryption,credentials,secret
Platform: UNKNOWN
